[
    {
        "id": "psy_001",
        "domain": "心理学常识",
        "type": "single",
        "question": "首先建立世界上第一个心理学实验室，被誉为科学心理学诞生标志的科学家是？",
        "options": [
            "弗洛伊德",
            "冯特",
            "皮亚杰",
            "马斯洛"
        ],
        "answer": [
            1
        ],
        "difficulty": "easy",
        "explanation": "威廉·冯特于1879年在莱比锡大学建立了世界上第一个心理学实验室。",
        "tags": [
            "心理学史",
            "冯特"
        ],
        "vector": {
            "教育学": 0.8,
            "理学": 0.5,
            "医学": 0.5,
            "管理学": 0.15
        }
    },
    {
        "id": "psy_002",
        "domain": "心理学常识",
        "type": "single",
        "question": "精神分析学派的创立者是谁？",
        "options": [
            "荣格",
            "阿德勒",
            "华生",
            "弗洛伊德"
        ],
        "answer": [
            3
        ],
        "difficulty": "easy",
        "explanation": "西格蒙德·弗洛伊德是精神分析学派的创始人。",
        "tags": [
            "心理学史",
            "精神分析"
        ],
        "vector": {
            "教育学": 0.8,
            "理学": 0.5,
            "医学": 0.5,
            "管理学": 0.15
        }
    },
    {
        "id": "psy_004",
        "domain": "心理学常识",
        "type": "single",
        "question": "首创需要层次理论，将人的需求分为生理、安全、爱与归属、尊重、自我实现五层的是？",
        "options": [
            "罗杰斯",
            "班杜拉",
            "马斯洛",
            "斯金纳"
        ],
        "answer": [
            2
        ],
        "difficulty": "easy",
        "explanation": "亚伯拉罕·马斯洛提出了著名的需求层次理论。",
        "tags": [
            "人本主义",
            "马斯洛"
        ],
        "vector": {
            "哲学": 1.0,
            "历史学": 0.5,
            "法学": 0.3,
            "教育学": 0.8,
            "理学": 0.5,
            "医学": 0.5,
            "管理学": 0.15
        }
    },
    {
        "id": "psy_008",
        "domain": "心理学常识",
        "type": "single",
        "question": "“旁观者效应”（或“责任分散效应”）核心指出？",
        "options": [
            "旁观者越多，救助行为越可能发生",
            "旁观者越多，个体提供帮助的概率越低",
            "个人的行为不受环境影响",
            "看到他人受伤会产生移情"
        ],
        "answer": [
            1
        ],
        "difficulty": "easy",
        "explanation": "旁观者效应指出，紧急情况下旁观者数量越多，每个人感到自己应负的责任就越少，救助概率降低。",
        "tags": [
            "社会心理学"
        ],
        "vector": {
            "法学": 0.7,
            "管理学": 0.5,
            "理学": 0.5,
            "教育学": 0.8,
            "医学": 0.5
        }
    },
    {
        "id": "psy_015",
        "domain": "心理学常识",
        "type": "multiple",
        "question": "心理学研究方法通常有哪些种类？",
        "options": [
            "实验法",
            "观察法",
            "调查法",
            "个案法"
        ],
        "answer": [
            0,
            1,
            2,
            3
        ],
        "difficulty": "easy",
        "explanation": "心理学通过极其多样的实证方法如实验、观察、问卷调查、深度个案分析等进行研究。",
        "tags": [
            "研究方法"
        ],
        "vector": {
            "教育学": 0.8,
            "理学": 0.6,
            "医学": 0.4,
            "管理学": 0.3
        }
    },
    {
        "id": "psy_003",
        "domain": "心理学常识",
        "type": "single",
        "question": "巴甫洛夫通过狗的唾液分泌实验提出了什么理论？",
        "options": [
            "操作性条件反射",
            "经典条件反射",
            "社会学习理论",
            "认知心理学"
        ],
        "answer": [
            1
        ],
        "difficulty": "medium",
        "explanation": "巴甫洛夫发现了条件反射的规律，提出经典条件反射理论。",
        "tags": [
            "行为主义",
            "条件反射"
        ],
        "vector": {
            "哲学": 1.0,
            "历史学": 0.5,
            "法学": 0.3,
            "教育学": 0.8,
            "理学": 0.5,
            "医学": 0.5,
            "管理学": 0.15
        }
    },
    {
        "id": "psy_005",
        "domain": "心理学常识",
        "type": "single",
        "question": "认知失调理论是由哪位心理学家提出的？",
        "options": [
            "费斯汀格",
            "勒温",
            "奥尔波特",
            "海德"
        ],
        "answer": [
            0
        ],
        "difficulty": "medium",
        "explanation": "莱昂·费斯汀格于1957年提出了认知失调理论，用于解释人们态度与行为不一致时的心理状态。",
        "tags": [
            "社会心理学",
            "认知失调"
        ],
        "vector": {
            "法学": 0.7,
            "管理学": 0.5,
            "理学": 0.5,
            "教育学": 0.8,
            "医学": 0.5
        }
    },
    {
        "id": "psy_006",
        "domain": "心理学常识",
        "type": "single",
        "question": "斯金纳箱实验主要验证了哪种心理学机制？",
        "options": [
            "经典条件反射",
            "操作性条件反射",
            "完形心理学",
            "建构主义"
        ],
        "answer": [
            1
        ],
        "difficulty": "medium",
        "explanation": "斯金纳通过老鼠杠杆实验等，提出并验证了操作性条件反射理论。",
        "tags": [
            "行为主义"
        ],
        "vector": {
            "哲学": 1.0,
            "历史学": 0.5,
            "法学": 0.3,
            "教育学": 0.8,
            "理学": 0.5,
            "医学": 0.5,
            "管理学": 0.15
        }
    },
    {
        "id": "psy_007",
        "domain": "心理学常识",
        "type": "single",
        "question": "马太效应（Matthew Effect）在社会心理学中通常指？",
        "options": [
            "近墨者黑",
            "旁观者效应",
            "赢家通吃、强者愈强",
            "破窗效应"
        ],
        "answer": [
            2
        ],
        "difficulty": "medium",
        "explanation": "马太效应指强者愈强、弱者愈弱的现象，广泛应用在心理学和社会学领域。",
        "tags": [
            "心理学效应"
        ],
        "vector": {
            "教育学": 0.8,
            "理学": 0.5,
            "医学": 0.5,
            "管理学": 0.15
        }
    },
    {
        "id": "psy_009",
        "domain": "心理学常识",
        "type": "single",
        "question": "人类短时记忆的广度一般为多少个组块（Chucks）？",
        "options": [
            "3±1",
            "7±2",
            "12±2",
            "无限"
        ],
        "answer": [
            1
        ],
        "difficulty": "medium",
        "explanation": "米勒（George Miller）提出人类短时记忆的容量大约为7±2个组块。",
        "tags": [
            "认知心理学",
            "记忆"
        ],
        "vector": {
            "教育学": 0.8,
            "理学": 0.5,
            "医学": 0.5,
            "管理学": 0.15
        }
    },
    {
        "id": "psy_012",
        "domain": "心理学常识",
        "type": "multiple",
        "question": "以下哪些心理学流派被称为心理学史上的前三大势力？",
        "options": [
            "精神分析学派",
            "行为主义学派",
            "人本主义学派",
            "进化心理学"
        ],
        "answer": [
            0,
            1,
            2
        ],
        "difficulty": "medium",
        "explanation": "行为主义被称为第一势力，精神分析是第二势力，人本主义被称为第三势力。",
        "tags": [
            "心理学流派"
        ],
        "vector": {
            "教育学": 0.8,
            "理学": 0.5,
            "医学": 0.5,
            "管理学": 0.15
        }
    },
    {
        "id": "psy_013",
        "domain": "心理学常识",
        "type": "multiple",
        "question": "人格特征的“大五人格”模型（Big Five）包括哪些维度？",
        "options": [
            "外向性",
            "宜人性",
            "神经质或情绪不稳定性",
            "压抑性"
        ],
        "answer": [
            0,
            1,
            2
        ],
        "difficulty": "hard",
        "explanation": "“大五”包含经验开放性、尽责性(宜人性)、外向性、神经质和严谨性（责任心）。压抑性不是大五人格的一个独立基本维度。",
        "tags": [
            "人格心理学",
            "大五"
        ],
        "vector": {
            "教育学": 0.8,
            "理学": 0.5,
            "医学": 0.5,
            "管理学": 0.15
        }
    },
    {
        "domain": "心理学常识",
        "type": "multiple",
        "difficulty": "medium",
        "question": "以下哪些属于认知偏差？",
        "options": [
            "确认偏差",
            "锚定效应",
            "多巴胺效应",
            "幸存者偏差"
        ],
        "answer": [
            0,
            1,
            3
        ],
        "explanation": "确认偏差、锚定效应、幸存者偏差均为认知偏差。多巴胺效应是神经生物学概念。",
        "tags": [
            "认知偏差",
            "心理学"
        ],
        "vector": {
            "教育学": 0.8,
            "理学": 0.5,
            "医学": 0.5,
            "管理学": 0.15
        },
        "id": "psy_016"
    },
    {
        "domain": "心理学常识",
        "type": "single",
        "difficulty": "hard",
        "question": "在心理测量学中，测验的信度(reliability)与效度(validity)的关系是什么？",
        "options": [
            "信度高则效度一定高",
            "效度高则信度一定高，但反之不成立",
            "两者完全独立",
            "信度是效度的上限"
        ],
        "answer": [
            1
        ],
        "explanation": "效度高的测验信度一定高(不可靠则不可能有效)，但高信度不一定高效度(系统偏差可稳定但测偏了)，效度≤√信度。",
        "tags": [
            "心理测量",
            "信效度"
        ],
        "vector": {
            "教育学": 0.8,
            "理学": 0.5,
            "医学": 0.5,
            "管理学": 0.15
        },
        "id": "psy_017"
    },
    {
        "domain": "心理学常识",
        "type": "single",
        "difficulty": "hard",
        "question": "在发展心理学中，'心理理论(Theory of Mind)'能力通常在儿童几岁时形成？",
        "options": [
            "1岁",
            "2岁",
            "4-5岁",
            "8岁"
        ],
        "answer": [
            2
        ],
        "explanation": "心理理论(理解他人有不同信念/想法)通常4-5岁通过错误信念任务(false belief task)，2-3岁有萌芽。",
        "tags": [
            "发展心理学",
            "心理理论"
        ],
        "vector": {
            "教育学": 0.8,
            "理学": 0.5,
            "医学": 0.5,
            "哲学": 1.0,
            "历史学": 0.5,
            "法学": 0.3,
            "管理学": 0.15
        },
        "id": "psy_018"
    },
    {
        "domain": "心理学常识",
        "type": "single",
        "difficulty": "hard",
        "question": "在神经科学中，镜像神经元的发现主要来自对哪种动物的研究？",
        "options": [
            "大鼠",
            "猕猴",
            "猫",
            "鸽子"
        ],
        "answer": [
            1
        ],
        "explanation": "Rizzolatti团队在猕猴F5区首次发现镜像神经元，执行动作和观察同类动作时均放电。",
        "tags": [
            "神经科学",
            "镜像神经元"
        ],
        "vector": {
            "教育学": 0.8,
            "理学": 0.5,
            "医学": 0.5,
            "管理学": 0.15
        },
        "id": "psy_019"
    },
    {
        "domain": "心理学常识",
        "type": "single",
        "difficulty": "hard",
        "question": "在记忆研究中，'工作记忆'模型(Baddeley & Hitch)中的中央执行系统的主要功能是什么？",
        "options": [
            "存储视觉信息",
            "协调和控制语音环路、视空模板等子系统",
            "长期存储",
            "情绪调节"
        ],
        "answer": [
            1
        ],
        "explanation": "中央执行系统(central executive)是注意力控制中心，协调语音环路、视空模板和情景缓冲器等子系统。",
        "tags": [
            "记忆",
            "工作记忆"
        ],
        "vector": {
            "教育学": 0.8,
            "理学": 0.5,
            "医学": 0.5,
            "管理学": 0.15
        },
        "id": "psy_020"
    },
    {
        "id": "psy_021",
        "domain": "心理学常识",
        "type": "single",
        "difficulty": "easy",
        "question": "弗洛伊德将人格结构分为哪三个部分？",
        "options": [
            "本我、自我、超我",
            "意识、前意识、潜意识",
            "理性、感性、本能",
            "内倾、外倾、中间"
        ],
        "answer": [
            0
        ],
        "explanation": "弗洛伊德人格结构：本我(Id, 快乐原则)、自我(Ego, 现实原则)、超我(Superego, 道德原则)。",
        "tags": [
            "弗洛伊德",
            "人格"
        ],
        "vector": {
            "教育学": 0.8,
            "理学": 0.5,
            "医学": 0.5,
            "管理学": 0.15
        }
    },
    {
        "id": "psy_022",
        "domain": "心理学常识",
        "type": "single",
        "difficulty": "easy",
        "question": "马斯洛需求层次理论中，最高层次的需求是什么？",
        "options": [
            "尊重需求",
            "安全需求",
            "自我实现需求",
            "社交需求"
        ],
        "answer": [
            2
        ],
        "explanation": "马斯洛金字塔从低到高：生理→安全→社交→尊重→自我实现。",
        "tags": [
            "马斯洛",
            "需求层次"
        ],
        "vector": {
            "教育学": 0.8,
            "理学": 0.5,
            "医学": 0.5,
            "管理学": 0.15
        }
    },
    {
        "id": "psy_023",
        "domain": "心理学常识",
        "type": "multiple",
        "difficulty": "easy",
        "question": "以下哪些是心理学的基本研究方法？",
        "options": [
            "观察法",
            "实验法",
            "调查法",
            "占卜法"
        ],
        "answer": [
            0,
            1,
            2
        ],
        "explanation": "观察法、实验法、调查法是心理学三大基本方法，占卜不是科学研究方法。",
        "tags": [
            "研究方法",
            "心理学"
        ],
        "vector": {
            "教育学": 0.8,
            "理学": 0.5,
            "医学": 0.5,
            "管理学": 0.15
        }
    },
    {
        "id": "psy_024",
        "domain": "心理学常识",
        "type": "single",
        "difficulty": "medium",
        "question": "在斯金纳的操作性条件作用中，'负强化'是指什么？",
        "options": [
            "呈现厌恶刺激以减少行为",
            "移除厌恶刺激以增加行为频率",
            "不给予任何刺激",
            "给予愉快刺激以增加行为"
        ],
        "answer": [
            1
        ],
        "explanation": "负强化=移除厌恶刺激→行为增加(如吃药消除疼痛→以后更愿吃药)。惩罚=呈现/移除刺激→行为减少。",
        "tags": [
            "行为主义",
            "强化"
        ],
        "vector": {
            "哲学": 1.0,
            "历史学": 0.5,
            "法学": 0.3,
            "教育学": 0.8,
            "理学": 0.5,
            "医学": 0.5,
            "管理学": 0.15
        }
    },
    {
        "id": "psy_025",
        "domain": "心理学常识",
        "type": "single",
        "difficulty": "medium",
        "question": "在艾森克的人格理论中，内向-外向维度的生理基础是什么？",
        "options": [
            "大脑皮层唤醒水平",
            "多巴胺水平",
            "血清素水平",
            "杏仁核大小"
        ],
        "answer": [
            0
        ],
        "explanation": "艾森克认为内向者基础唤醒水平高(因此回避强刺激)，外向者唤醒水平低(因此寻求强刺激)。",
        "tags": [
            "人格",
            "艾森克"
        ],
        "vector": {
            "教育学": 0.8,
            "理学": 0.5,
            "医学": 0.5,
            "管理学": 0.15
        }
    },
    {
        "id": "psy_026",
        "domain": "心理学常识",
        "type": "single",
        "difficulty": "medium",
        "question": "'习得性无助'(Learned Helplessness)概念最初来自对什么动物的实验？",
        "options": [
            "小白鼠",
            "狗",
            "猴子",
            "鸽子"
        ],
        "answer": [
            1
        ],
        "explanation": "Seligman和Maier 1967年用狗做穿梭箱实验，发现无法逃避电击的狗后来也不再尝试逃避，提出习得性无助。",
        "tags": [
            "习得性无助",
            "实验"
        ],
        "vector": {
            "教育学": 0.8,
            "理学": 0.5,
            "医学": 0.5,
            "管理学": 0.15
        }
    },
    {
        "id": "psy_027",
        "domain": "心理学常识",
        "type": "single",
        "difficulty": "hard",
        "question": "在积极心理学中，Seligman的PERMA模型中'A'代表什么？",
        "options": [
            "Achievement(成就)",
            "Awareness(觉察)",
            "Attachment(依恋)",
            "Autonomy(自主)"
        ],
        "answer": [
            0
        ],
        "explanation": "PERMA=P(积极情绪)+E(投入)+R(人际关系)+M(意义)+A(成就)，是Seligman的幸福五要素。",
        "tags": [
            "积极心理学",
            "PERMA"
        ],
        "vector": {
            "教育学": 0.8,
            "理学": 0.5,
            "医学": 0.5,
            "管理学": 0.15
        }
    },
    {
        "id": "psy_028",
        "domain": "心理学常识",
        "type": "multiple",
        "difficulty": "hard",
        "question": "关于斯特鲁普效应(Stroop Effect)，以下哪些描述正确？",
        "options": [
            "命名颜色字体与字义不一致的词时反应变慢",
            "反映了自动化加工与控制加工的冲突",
            "只出现在视觉通道",
            "前额叶损伤患者效应更明显"
        ],
        "answer": [
            0,
            1,
            3
        ],
        "explanation": "斯特鲁普效应体现自动阅读与控制颜色命名的冲突，前额叶受损者更难抑制自动加工，效应更明显。听觉也有类似效应。",
        "tags": [
            "斯特鲁普",
            "认知"
        ],
        "vector": {
            "教育学": 0.8,
            "理学": 0.5,
            "医学": 0.5,
            "管理学": 0.15
        }
    }
]